pesos/__init__.py
pesos/detector.py
pesos/executor.py
pesos/scheduler.py
pesos/testing.py
pesos/util.py
pesos/vendor/__init__.py
pesos/vendor/mesos/__init__.py
pesos/vendor/mesos/mesos_pb2.py
pesos/vendor/mesos/authentication/__init__.py
pesos/vendor/mesos/authentication/authentication_pb2.py
pesos/vendor/mesos/containerizer/__init__.py
pesos/vendor/mesos/containerizer/containerizer_pb2.py
pesos/vendor/mesos/fetcher/__init__.py
pesos/vendor/mesos/fetcher/fetcher_pb2.py
pesos/vendor/mesos/internal/__init__.py
pesos/vendor/mesos/internal/log_pb2.py
pesos/vendor/mesos/internal/messages_pb2.py
pesos/vendor/mesos/internal/registry_pb2.py
pesos/vendor/mesos/internal/state_pb2.py
pesos/vendor/mesos/module/__init__.py
pesos/vendor/mesos/module/module_pb2.py
pesos/vendor/mesos/scheduler/__init__.py
pesos/vendor/mesos/scheduler/scheduler_pb2.py
pesos-0.2.2.dist-info/DESCRIPTION.rst
pesos-0.2.2.dist-info/METADATA
pesos-0.2.2.dist-info/metadata.json
pesos-0.2.2.dist-info/RECORD
pesos-0.2.2.dist-info/top_level.txt
pesos-0.2.2.dist-info/WHEEL
pesos-0.2.2.dist-info/zip-safe
