Metadata-Version: 2.0
Name: pesos
Version: 0.2.2
Summary: Pure python implementation of the Apache Mesos Framework API
Home-page: http://github.com/wickman/pesos
Author: Brian Wickman
Author-email: wickman@gmail.com
License: Apache License 2.0
Platform: UNKNOWN
Requires-Dist: compactor[pb] (==0.2.2)
Requires-Dist: futures (==2.1.6)
Requires-Dist: mesos.interface (==0.21.1)
